prometheus_givenergy/__init__.py
prometheus_givenergy/__main__.py
prometheus_givenergy/prometheus.py
prometheus_givenergy/register.py
prometheus_givenergy-1.0.3.dist-info/LICENSE
prometheus_givenergy-1.0.3.dist-info/METADATA
prometheus_givenergy-1.0.3.dist-info/WHEEL
prometheus_givenergy-1.0.3.dist-info/entry_points.txt
prometheus_givenergy-1.0.3.dist-info/top_level.txt
prometheus_givenergy-1.0.3.dist-info/RECORD
