Metadata-Version: 2.1
Name: prometheus-givenergy
Version: 1.0.3
Summary: prometheus exporter for GivEnergy inverter metrics.
Author-email: Barry Scott <barry@barrys-emacs.org>
License: Apache-2.0
Project-URL: Homepage, https://github.com/barry-scott/prometheus_givenergy
Project-URL: Bug Tracker, https://github.com/barry-scott/prometheus_givenergy/issues
Keywords: development
Classifier: Intended Audience :: End Users/Desktop
Classifier: Topic :: Utilities
Classifier: Environment :: Console
Classifier: Programming Language :: Python :: 3
Requires-Python: >=3.10
License-File: LICENSE
Requires-Dist: pymodbus
Requires-Dist: crccheck
